pyTooling/CLIAbstraction/Argument.py
pyTooling/CLIAbstraction/BooleanFlag.py
pyTooling/CLIAbstraction/Command.py
pyTooling/CLIAbstraction/Flag.py
pyTooling/CLIAbstraction/KeyValueFlag.py
pyTooling/CLIAbstraction/OptionalValuedFlag.py
pyTooling/CLIAbstraction/ValuedFlag.py
pyTooling/CLIAbstraction/ValuedFlagList.py
pyTooling/CLIAbstraction/ValuedTupleFlag.py
pyTooling/CLIAbstraction/__init__.py
pyTooling.CLIAbstraction-0.4.1.dist-info/LICENSE.md
pyTooling.CLIAbstraction-0.4.1.dist-info/METADATA
pyTooling.CLIAbstraction-0.4.1.dist-info/WHEEL
pyTooling.CLIAbstraction-0.4.1.dist-info/top_level.txt
pyTooling.CLIAbstraction-0.4.1.dist-info/RECORD
