Metadata-Version: 2.1
Name: pyTooling.CLIAbstraction
Version: 0.4.1
Summary: Basic abstraction layer for executables.
Home-page: https://GitHub.com/pyTooling/pyTooling.CLIAbstraction
Author: Patrick Lehmann
Author-email: Paebbels@gmail.com
License: Apache-2.0
Project-URL: Documentation, https://pyTooling.GitHub.io/pyTooling.CLIAbstraction
Project-URL: Source Code, https://GitHub.com/pyTooling/pyTooling.CLIAbstraction
Project-URL: Issue Tracker, https://GitHub.com/pyTooling/pyTooling.CLIAbstraction/issues
Keywords: abstract,executable,cli,cli arguments
Classifier: Topic :: Scientific/Engineering :: Electronic Design Automation (EDA)
Classifier: License :: OSI Approved :: Apache Software License
Classifier: Programming Language :: Python :: 3 :: Only
Classifier: Programming Language :: Python :: 3.7
Classifier: Programming Language :: Python :: 3.8
Classifier: Programming Language :: Python :: 3.9
Classifier: Programming Language :: Python :: 3.10
Classifier: Programming Language :: Python :: 3.11
Classifier: Development Status :: 4 - Beta
Requires-Python: >=3.7
License-File: LICENSE.md
Requires-Dist: pyAttributes (>=2.5.1)
Requires-Dist: pyTooling (>=5.0.0)
Provides-Extra: all
Requires-Dist: pyAttributes (>=2.5.1) ; extra == 'all'
Requires-Dist: autoapi (>=2.0.1) ; extra == 'all'
Requires-Dist: sphinx-fontawesome (>=0.0.6) ; extra == 'all'
Requires-Dist: sphinxcontrib-mermaid (>=0.7.1) ; extra == 'all'
Requires-Dist: sphinx-autodoc-typehints (>=1.19.5) ; extra == 'all'
Requires-Dist: pyTooling (>=5.0.0) ; extra == 'all'
Requires-Dist: sphinx (>=5.3.0) ; extra == 'all'
Provides-Extra: doc
Requires-Dist: pyAttributes (>=2.5.1) ; extra == 'doc'
Requires-Dist: autoapi (>=2.0.1) ; extra == 'doc'
Requires-Dist: sphinx-fontawesome (>=0.0.6) ; extra == 'doc'
Requires-Dist: sphinxcontrib-mermaid (>=0.7.1) ; extra == 'doc'
Requires-Dist: sphinx-autodoc-typehints (>=1.19.5) ; extra == 'doc'
Requires-Dist: pyTooling (>=5.0.0) ; extra == 'doc'
Requires-Dist: sphinx (>=5.3.0) ; extra == 'doc'
